README.md
setup.cfg
setup.py
FBTools/Automation1.py
FBTools/CreateAccount.py
FBTools/Friend.py
FBTools/GetInfo.py
FBTools/GetToken.py
FBTools/Login.py
FBTools/Privacy.py
FBTools/Setting.py
FBTools/Tools.py
FBTools/__init__.py
fbtoolsbox.egg-info/PKG-INFO
fbtoolsbox.egg-info/SOURCES.txt
fbtoolsbox.egg-info/dependency_links.txt
fbtoolsbox.egg-info/requires.txt
fbtoolsbox.egg-info/top_level.txt